cryptowrench/blockchain/bitcoin.py
cryptowrench/wallet/__init__.py
cryptowrench/wallet/helpers/adresses/__init__.py
cryptowrench/wallet/helpers/adresses/bitcoin.py
cryptowrench/wallet/helpers/adresses/ethereum.py
cryptowrench/wallet/helpers/adresses/main.py
cryptowrench/wallet/helpers/block_explorer.py
cryptowrench/wallet/helpers/derivation_path.py
cryptowrench/wallet/helpers/elliptic_math.py
cryptowrench/wallet/helpers/hashfuncs.py
cryptowrench/wallet/helpers/hd_wallet.py
cryptowrench/wallet/helpers/key_validation.py
cryptowrench/wallet/helpers/keys.py
cryptowrench/wallet/helpers/serialize.py
cryptowrench/wallet/main.py
cryptowrench-0.1.7.dist-info/LICENSE
cryptowrench-0.1.7.dist-info/WHEEL
cryptowrench-0.1.7.dist-info/METADATA
cryptowrench-0.1.7.dist-info/RECORD
