Metadata-Version: 2.1
Name: cryptowrench
Version: 0.1.7
Summary: A set of tools for nerding around with crypto.
License: MIT
Author: Federico Giancarelli
Author-email: hello@federicogiancarelli.com
Requires-Python: >=3.9,<4.0
Classifier: License :: OSI Approved :: MIT License
Classifier: Programming Language :: Python :: 3
Classifier: Programming Language :: Python :: 3.9
Classifier: Programming Language :: Python :: 3.10
Requires-Dist: base58 (>=2.1.1,<3.0.0)
Requires-Dist: bech32 (>=1.2.0,<2.0.0)
Requires-Dist: crypography (>=37.0.4,<38.0.0)
Requires-Dist: mnemonic (>=0.20,<0.21)
Requires-Dist: pycryptodome (>=3.15.0,<4.0.0)
